mlm_pytorch/__init__.py
mlm_pytorch/mlm_pytorch.py
mlm_pytorch-0.1.0.dist-info/LICENSE
mlm_pytorch-0.1.0.dist-info/METADATA
mlm_pytorch-0.1.0.dist-info/WHEEL
mlm_pytorch-0.1.0.dist-info/top_level.txt
mlm_pytorch-0.1.0.dist-info/RECORD
