Metadata-Version: 2.1
Name: mlm-pytorch
Version: 0.1.0
Summary: MLM (Masked Language Modeling) - Pytorch
Home-page: https://github.com/lucidrains/mlm-pytorch
Author: Phil Wang
Author-email: lucidrains@gmail.com
License: MIT
Keywords: transformers,artificial intelligence,pretraining,unsupervised learning
Platform: UNKNOWN
Classifier: Development Status :: 4 - Beta
Classifier: Intended Audience :: Developers
Classifier: Topic :: Scientific/Engineering :: Artificial Intelligence
Classifier: License :: OSI Approved :: MIT License
Classifier: Programming Language :: Python :: 3.6
License-File: LICENSE
Requires-Dist: torch (>=1.1.0)
